XOR/design.sv
// Porta XOR
module xor_gate (a,b,y);
  input a,b;
  output y;
  
  // estrutural:
  wire      abar, bbar, t1, t2;
  not invA (abar, a);
  not invB (bbar, b);
  and and1 (t1, a, bbar);
  and and2 (t2, b, abar);
  or  or1 (y, t1, t2);

  // comportamental
  //assign y=a^b;
endmodule

XOR/testbench.sv
// testbench Porta XOR
module xorgate_tb;
  reg A,B;
  wire Y;
  
  xor_gate xorg( .a(A), .b(B), .y(Y) );
  
  initial
    begin
       $dumpfile("dump.vcd");
  		$dumpvars(1);
    end
  
  initial
    begin
      $display("\t\tTempo, A, B, output= Y");
      $monitor($time,"  ", A, B," output= ", Y);
      
      //bit #1
      A = 1'b0;
      B = 1'b0;
      
      #1
      //bit #2
      A = 1'b1;
      B = 1'b0;
      
      #1
      //bit #3
      A = 1'b1;
      B = 1'b1;
      
      #1
      //bit #4
      A = 1'b0;
      B = 1'b0;
      
      #1
      //bit #5
      A = 1'b0;
      B = 1'b0;
      
      #3
      A = 1'b1;
      B = 1'b0;
      
      #2
      A = 1'b1;
      B = 1'b1;
      
      #2
      A = 1'b0;
      B = 1'b0;
      
      #2
      A = 1'b1;
      B = 1'b1;
      
            
      #1
      A = 1'b1;
      B = 1'b0;
      
      #1
      A = 1'b0;
      B = 1'b1;
      
      #1
      A = 1'b1;
      B = 1'b0;
      
      #1
      A = 1'b0;
      B = 1'b1;
      
      #1
      A = 1'b1;
      B = 1'b0;
      
      #1
      A = 1'b0;
      B = 1'b1;
      
      #1
      A = 1'b1;
      B = 1'b0;
      
      #1
      A = 1'b0;
      B = 1'b1;
      
      #5
      $display("fim");
    end
endmodule

XOR/dump.vcd
$date
	Mon Dec 11 19:06:39 2023
$end
$version
	Icarus Verilog
$end
$timescale
	1s
$end
$scope module xorgate_tb $end
$var wire 1 ! Y $end
$var reg 1 " A $end
$var reg 1 # B $end
$upscope $end
$enddefinitions $end
#0
$dumpvars
0#
0"
0!
$end
#1
1!
1"
#2
0!
1#
#3
0#
0"
#7
1!
1"
#9
0!
1#
#11
0#
0"
#13
0!
1#
1"
#14
1!
0#
#15
1#
0"
#16
1!
0#
1"
#17
1#
0"
#18
1!
0#
1"
#19
1#
0"
#20
1!
0#
1"
#21
1#
0"
